trimble/id/__init__.py
trimble/id/_constants.py
trimble/id/_version.py
trimble/id/analytics_http_client.py
trimble/id/bearer_token_http_client_provider.py
trimble/id/client_credential_token_provider.py
trimble/id/fixed_endpoint_provider.py
trimble/id/fixed_keyset_provider.py
trimble/id/fixed_token_provider.py
trimble/id/http_client.py
trimble/id/http_exception.py
trimble/id/open_id_endpoint_provider.py
trimble/id/open_id_keyset_provider.py
trimble/id/refreshable_token_provider.py
trimble/id/robust_http_client_provider.py
trimble/id/validated_claimset_provider.py
trimble_id-0.1.1.dist-info/LICENSE
trimble_id-0.1.1.dist-info/METADATA
trimble_id-0.1.1.dist-info/WHEEL
trimble_id-0.1.1.dist-info/top_level.txt
trimble_id-0.1.1.dist-info/RECORD
