Metadata-Version: 2.2
Name: trimble-id
Version: 0.1.1
Summary: Trimble Authentication module Client Library for Python
Home-page: https://github.com/trimble-oss/trimble-id-sdk-docs-for-python
Author: Trimble Inc.
Author-email: sdk@trimble.com
License: MIT License
Keywords: Trimble,TrimbleID,Trimble Identity
Classifier: Programming Language :: Python
Classifier: Programming Language :: Python :: 3 :: Only
Classifier: License :: OSI Approved :: MIT License
Classifier: Operating System :: OS Independent
License-File: LICENSE
Requires-Dist: aiohttp>=3.7.4
Requires-Dist: PyJWT>=2.4.0
Requires-Dist: requests>=2.28.1
Requires-Dist: cryptography>=38.0.3
Dynamic: author
Dynamic: author-email
Dynamic: classifier
Dynamic: description
Dynamic: description-content-type
Dynamic: home-page
Dynamic: keywords
Dynamic: license
Dynamic: requires-dist
Dynamic: summary
